trackmania/__init__.py
trackmania/gbx_remote_client.py
trackmania/trackmania_client.py
trackmania_nations_forever_client-0.1.1.dist-info/METADATA
trackmania_nations_forever_client-0.1.1.dist-info/WHEEL
trackmania_nations_forever_client-0.1.1.dist-info/top_level.txt
trackmania_nations_forever_client-0.1.1.dist-info/RECORD
