Metadata-Version: 2.1
Name: trackmania-nations-forever-client
Version: 0.1.1
Summary: An XML RPC client for Trackmania Nations Forever dedicated servers.
Home-page: https://github.com/Kaindorf-Games/trackmania-nations-forever-client
License: UNKNOWN
Platform: UNKNOWN
